[
  {
    "inputs": [],
    "stateMutability": "nonpayable",
    "type": "constructor"
  },
  {
    "anonymous": false,
    "inputs": [
      {
        "indexed": false,
        "internalType": "address",
        "name": "_admin",
        "type": "address"
      }
    ],
    "name": "AdminAdded",
    "type": "event"
  },
  {
    "anonymous": false,
    "inputs": [
      {
        "indexed": false,
        "internalType": "address",
        "name": "_gc",
        "type": "address"
      }
    ],
    "name": "GCAdded",
    "type": "event"
  },
  {
    "anonymous": false,
    "inputs": [
      {
        "indexed": false,
        "internalType": "address",
        "name": "_owner",
        "type": "address"
      }
    ],
    "name": "OwnerAdded",
    "type": "event"
  },
  {
    "anonymous": false,
    "inputs": [
      {
        "indexed": false,
        "internalType": "uint256",
        "name": "_index",
        "type": "uint256"
      }
    ],
    "name": "ProjectAdded",
    "type": "event"
  },
  {
    "anonymous": false,
    "inputs": [
      {
        "indexed": false,
        "internalType": "address",
        "name": "_project",
        "type": "address"
      },
      {
        "indexed": false,
        "internalType": "uint256",
        "name": "_value",
        "type": "uint256"
      }
    ],
    "name": "ProjectFunded",
    "type": "event"
  },
  {
    "anonymous": false,
    "inputs": [
      {
        "indexed": false,
        "internalType": "address",
        "name": "_project",
        "type": "address"
      },
      {
        "indexed": false,
        "internalType": "uint256",
        "name": "_task",
        "type": "uint256"
      }
    ],
    "name": "TaskFunded",
    "type": "event"
  },
  {
    "inputs": [],
    "name": "projectSerial",
    "outputs": [
      {
        "internalType": "uint256",
        "name": "",
        "type": "uint256"
      }
    ],
    "stateMutability": "view",
    "type": "function",
    "constant": true
  },
  {
    "inputs": [
      {
        "internalType": "uint256",
        "name": "",
        "type": "uint256"
      }
    ],
    "name": "projects",
    "outputs": [
      {
        "internalType": "address",
        "name": "",
        "type": "address"
      }
    ],
    "stateMutability": "view",
    "type": "function",
    "constant": true
  },
  {
    "inputs": [
      {
        "internalType": "address",
        "name": "",
        "type": "address"
      }
    ],
    "name": "roles",
    "outputs": [
      {
        "internalType": "uint256",
        "name": "",
        "type": "uint256"
      }
    ],
    "stateMutability": "view",
    "type": "function",
    "constant": true
  },
  {
    "inputs": [
      {
        "internalType": "address",
        "name": "_admin",
        "type": "address"
      }
    ],
    "name": "enrollAdmin",
    "outputs": [],
    "stateMutability": "nonpayable",
    "type": "function"
  },
  {
    "inputs": [
      {
        "internalType": "address",
        "name": "_owner",
        "type": "address"
      }
    ],
    "name": "enrollOwner",
    "outputs": [],
    "stateMutability": "nonpayable",
    "type": "function"
  },
  {
    "inputs": [
      {
        "internalType": "address",
        "name": "_gc",
        "type": "address"
      }
    ],
    "name": "enrollGC",
    "outputs": [],
    "stateMutability": "nonpayable",
    "type": "function"
  },
  {
    "inputs": [
      {
        "internalType": "address",
        "name": "_owner",
        "type": "address"
      },
      {
        "internalType": "uint256[]",
        "name": "fees",
        "type": "uint256[]"
      }
    ],
    "name": "newProject",
    "outputs": [
      {
        "internalType": "address",
        "name": "_at",
        "type": "address"
      }
    ],
    "stateMutability": "nonpayable",
    "type": "function"
  },
  {
    "inputs": [
      {
        "internalType": "address",
        "name": "_project",
        "type": "address"
      },
      {
        "internalType": "uint256",
        "name": "_task",
        "type": "uint256"
      }
    ],
    "name": "fundTask",
    "outputs": [
      {
        "internalType": "uint256",
        "name": "_minted",
        "type": "uint256"
      }
    ],
    "stateMutability": "nonpayable",
    "type": "function"
  },
  {
    "inputs": [
      {
        "internalType": "address",
        "name": "_project",
        "type": "address"
      }
    ],
    "name": "fundProject",
    "outputs": [
      {
        "internalType": "uint256",
        "name": "_minted",
        "type": "uint256"
      }
    ],
    "stateMutability": "nonpayable",
    "type": "function"
  },
  {
    "inputs": [
      {
        "internalType": "address",
        "name": "_of",
        "type": "address"
      }
    ],
    "name": "balance",
    "outputs": [
      {
        "internalType": "uint256",
        "name": "_tokens",
        "type": "uint256"
      }
    ],
    "stateMutability": "view",
    "type": "function",
    "constant": true
  }
]
